<?xml version="1.0" encoding="ISO-8859-1"?>

<history configuration="config/auction.xml">
	<agents>
		<agent name="Xines">
			<vehicle name="Vehicle 1"/>
			<vehicle name="Vehicle 2"/>
		</agent>
		<agent name="JB-est-low">
			<vehicle name="Vehicle 3"/>
			<vehicle name="Vehicle 4"/>
		</agent>
	</agents>
	<rounds>
		<round id="1">
			<tasks>
				<task id="0" pickup="Cardiff" delivery="Sheffield" weight="3" reward="69479">
					<bid agent="Xines" bid="876"/>
					<bid agent="JB-est-low" bid="1008"/>
				</task>
				<task id="1" pickup="Manchester" delivery="Norwich" weight="3" reward="47516">
					<bid agent="Xines" bid="893"/>
					<bid agent="JB-est-low" bid="994"/>
				</task>
				<task id="2" pickup="Cardiff" delivery="Manchester" weight="3" reward="68638">
					<bid agent="Xines" bid="496"/>
					<bid agent="JB-est-low" bid="1163"/>
				</task>
				<task id="3" pickup="Sheffield" delivery="Portsmouth" weight="3" reward="55553">
					<bid agent="Xines" bid="746"/>
					<bid agent="JB-est-low" bid="2271"/>
				</task>
				<task id="4" pickup="Liverpool" delivery="Norwich" weight="3" reward="41305">
					<bid agent="Xines" bid="1968"/>
					<bid agent="JB-est-low" bid="2837"/>
				</task>
				<task id="5" pickup="Norwich" delivery="London" weight="3" reward="85625">
					<bid agent="Xines" bid="1392"/>
					<bid agent="JB-est-low" bid="496"/>
				</task>
				<task id="6" pickup="Cardiff" delivery="London" weight="3" reward="64503">
					<bid agent="Xines" bid="1035"/>
					<bid agent="JB-est-low" bid="2336"/>
				</task>
				<task id="7" pickup="London" delivery="Manchester" weight="3" reward="68101">
					<bid agent="Xines" bid="851"/>
					<bid agent="JB-est-low" bid="1080"/>
				</task>
				<task id="8" pickup="Plymouth" delivery="Birmingham" weight="3" reward="41269">
					<bid agent="Xines" bid="2430"/>
					<bid agent="JB-est-low" bid="1811"/>
				</task>
				<task id="9" pickup="Portsmouth" delivery="Plymouth" weight="3" reward="75780">
					<bid agent="Xines" bid="1445"/>
					<bid agent="JB-est-low" bid="1269"/>
				</task>
				<task id="10" pickup="Birmingham" delivery="Cardiff" weight="3" reward="85625">
					<bid agent="Xines" bid="517"/>
					<bid agent="JB-est-low" bid="595"/>
				</task>
				<task id="11" pickup="Portsmouth" delivery="Sheffield" weight="3" reward="55553">
					<bid agent="Xines" bid="561"/>
					<bid agent="JB-est-low" bid="496"/>
				</task>
				<task id="12" pickup="Cardiff" delivery="Manchester" weight="3" reward="68638">
					<bid agent="Xines" bid="944"/>
					<bid agent="JB-est-low" bid="496"/>
				</task>
				<task id="13" pickup="Newcastle" delivery="Manchester" weight="3" reward="69390">
					<bid agent="Xines" bid="1533"/>
					<bid agent="JB-est-low" bid="1334"/>
				</task>
				<task id="14" pickup="Portsmouth" delivery="Liverpool" weight="3" reward="48501">
					<bid agent="Xines" bid="635"/>
					<bid agent="JB-est-low" bid="496"/>
				</task>
				<task id="15" pickup="Sheffield" delivery="Liverpool" weight="3" reward="85840">
					<bid agent="Xines" bid="611"/>
					<bid agent="JB-est-low" bid="496"/>
				</task>
				<task id="16" pickup="London" delivery="Birmingham" weight="3" reward="85088">
					<bid agent="Xines" bid="495"/>
					<bid agent="JB-est-low" bid="496"/>
				</task>
				<task id="17" pickup="Portsmouth" delivery="Norwich" weight="3" reward="72236">
					<bid agent="Xines" bid="495"/>
					<bid agent="JB-est-low" bid="1066"/>
				</task>
				<task id="18" pickup="Plymouth" delivery="Norwich" weight="3" reward="41806">
					<bid agent="Xines" bid="1275"/>
					<bid agent="JB-est-low" bid="1060"/>
				</task>
				<task id="19" pickup="Cardiff" delivery="Leeds" weight="3" reward="62087">
					<bid agent="Xines" bid="495"/>
					<bid agent="JB-est-low" bid="495"/>
				</task>
			</tasks>
			<events>
				<event id="0" time="0" vehicle="Vehicle 2" pickup="16"/>
				<event id="1" time="0" vehicle="Vehicle 3" pickup="18"/>
				<event id="2" time="300000000" vehicle="Vehicle 2" pickup="7"/>
				<event id="3" time="300000000" vehicle="Vehicle 3" pickup="8"/>
				<event id="4" time="600000000" vehicle="Vehicle 2" move="Birmingham"/>
				<event id="5" time="600000000" vehicle="Vehicle 3" move="Portsmouth"/>
				<event id="6" time="1911111111" vehicle="Vehicle 2" deliver="16"/>
				<event id="7" time="2211111110" vehicle="Vehicle 2" pickup="10"/>
				<event id="8" time="2488888888" vehicle="Vehicle 3" pickup="11"/>
				<event id="9" time="2511111110" vehicle="Vehicle 2" move="Cardiff"/>
				<event id="10" time="2788888888" vehicle="Vehicle 3" pickup="14"/>
				<event id="11" time="3088888887" vehicle="Vehicle 3" pickup="9"/>
				<event id="12" time="3388888887" vehicle="Vehicle 3" move="Plymouth"/>
				<event id="13" time="3788888886" vehicle="Vehicle 2" pickup="19"/>
				<event id="14" time="4088888885" vehicle="Vehicle 2" deliver="10"/>
				<event id="15" time="4388888885" vehicle="Vehicle 2" pickup="6"/>
				<event id="16" time="4688888885" vehicle="Vehicle 2" pickup="2"/>
				<event id="17" time="4988888885" vehicle="Vehicle 2" pickup="0"/>
				<event id="18" time="5277777775" vehicle="Vehicle 3" deliver="9"/>
				<event id="19" time="5288888884" vehicle="Vehicle 2" move="Birmingham"/>
				<event id="20" time="5577777775" vehicle="Vehicle 3" move="Portsmouth"/>
				<event id="21" time="6566666661" vehicle="Vehicle 2" move="Manchester"/>
				<event id="22" time="7466666663" vehicle="Vehicle 3" move="London"/>
				<event id="23" time="7621111105" vehicle="Vehicle 2" deliver="7"/>
				<event id="24" time="7921111105" vehicle="Vehicle 2" deliver="2"/>
				<event id="25" time="8221111104" vehicle="Vehicle 2" pickup="1"/>
				<event id="26" time="8297777773" vehicle="Vehicle 3" move="Norwich"/>
				<event id="27" time="8521111104" vehicle="Vehicle 2" move="Liverpool"/>
				<event id="28" time="8906666659" vehicle="Vehicle 2" pickup="4"/>
				<event id="29" time="9206666658" vehicle="Vehicle 2" move="Leeds"/>
				<event id="30" time="9575555550" vehicle="Vehicle 3" deliver="18"/>
				<event id="31" time="9875555550" vehicle="Vehicle 3" pickup="5"/>
				<event id="32" time="10012222213" vehicle="Vehicle 2" deliver="19"/>
				<event id="33" time="10175555549" vehicle="Vehicle 3" move="London"/>
				<event id="34" time="10312222213" vehicle="Vehicle 2" move="Sheffield"/>
				<event id="35" time="10771111101" vehicle="Vehicle 2" pickup="3"/>
				<event id="36" time="11071111100" vehicle="Vehicle 2" deliver="0"/>
				<event id="37" time="11371111100" vehicle="Vehicle 2" move="Birmingham"/>
				<event id="38" time="11453333326" vehicle="Vehicle 3" deliver="5"/>
				<event id="39" time="11753333326" vehicle="Vehicle 3" move="Birmingham"/>
				<event id="40" time="12373333321" vehicle="Vehicle 2" move="London"/>
				<event id="41" time="13064444436" vehicle="Vehicle 3" move="Cardiff"/>
				<event id="42" time="13684444431" vehicle="Vehicle 2" deliver="6"/>
				<event id="43" time="13984444431" vehicle="Vehicle 2" move="Portsmouth"/>
				<event id="44" time="14342222213" vehicle="Vehicle 3" pickup="12"/>
				<event id="45" time="14642222213" vehicle="Vehicle 3" move="Birmingham"/>
				<event id="46" time="14815555541" vehicle="Vehicle 2" pickup="17"/>
				<event id="47" time="15115555540" vehicle="Vehicle 2" deliver="3"/>
				<event id="48" time="15415555540" vehicle="Vehicle 2" move="London"/>
				<event id="49" time="15919999990" vehicle="Vehicle 3" deliver="8"/>
				<event id="50" time="16219999990" vehicle="Vehicle 3" move="Sheffield"/>
				<event id="51" time="16246666650" vehicle="Vehicle 2" move="Norwich"/>
				<event id="52" time="17222222212" vehicle="Vehicle 3" pickup="15"/>
				<event id="53" time="17522222212" vehicle="Vehicle 3" deliver="11"/>
				<event id="54" time="17524444427" vehicle="Vehicle 2" deliver="17"/>
				<event id="55" time="17822222212" vehicle="Vehicle 3" move="Leeds"/>
				<event id="56" time="17824444427" vehicle="Vehicle 2" deliver="4"/>
				<event id="57" time="18124444426" vehicle="Vehicle 2" deliver="1"/>
				<event id="58" time="18281111100" vehicle="Vehicle 3" move="Newcastle"/>
				<event id="59" time="19375555543" vehicle="Vehicle 3" pickup="13"/>
				<event id="60" time="19675555543" vehicle="Vehicle 3" move="Leeds"/>
				<event id="61" time="20769999987" vehicle="Vehicle 3" move="Liverpool"/>
				<event id="62" time="21575555542" vehicle="Vehicle 3" deliver="15"/>
				<event id="63" time="21875555542" vehicle="Vehicle 3" deliver="14"/>
				<event id="64" time="22175555541" vehicle="Vehicle 3" move="Manchester"/>
				<event id="65" time="22561111096" vehicle="Vehicle 3" deliver="12"/>
				<event id="66" time="22861111096" vehicle="Vehicle 3" deliver="13"/>
			</events>
		</round>
	</rounds>
	<statistics>
		<stat rank="1" agent="Xines">
			<total-tasks value="11"/>
			<total-distance value="1064.2"/>
			<total-cost value="5321"/>
			<total-reward value="8867"/>
			<total-profit value="3546"/>
		</stat>
		<stat rank="2" agent="JB-est-low">
			<total-tasks value="9"/>
			<total-distance value="1598.5"/>
			<total-cost value="7993"/>
			<total-reward value="7954"/>
			<total-profit value="-39"/>
		</stat>
	</statistics>
</history>
